README.md
sample.json
setup.cfg
setup.py
Gandyndns.egg-info/PKG-INFO
Gandyndns.egg-info/SOURCES.txt
Gandyndns.egg-info/dependency_links.txt
Gandyndns.egg-info/requires.txt
Gandyndns.egg-info/top_level.txt
gandyndns/__init__.py
scripts/gandyndns