Metadata-Version: 2.1
Name: Gandyndns
Version: 0.3
Summary: Gandi dynamic ip updater.
Home-page: https://github.com/marmeladema/gandyndns
Author: Elie ROUDNINSKI
Author-email: xademax@gmail.com
License: MIT
Download-URL: https://github.com/marmeladema/gandyndns/archive/0.3.tar.gz
Keywords: gandi dyndns
Platform: UNKNOWN
Classifier: Development Status :: 3 - Alpha
Classifier: Topic :: Utilities
Classifier: License :: OSI Approved :: MIT License
Requires-Python: >=3
